{
	"textures": [
		{
			"image": "sprites/spells-0.webp",
			"format": "RGBA8888",
			"size": {
				"w": 2025,
				"h": 1982
			},
			"scale": 1,
			"frames": [
				{
					"filename": "mind_boost_2.png",
					"rotated": false,
					"trimmed": false,
					"sourceSize": {
						"w": 1100,
						"h": 1100
					},
					"spriteSourceSize": {
						"x": 0,
						"y": 0,
						"w": 1100,
						"h": 1100
					},
					"frame": {
						"x": 1,
						"y": 1,
						"w": 1100,
						"h": 1100
					}
				},
				{
					"filename": "mind_boost.png",
					"rotated": false,
					"trimmed": false,
					"sourceSize": {
						"w": 900,
						"h": 900
					},
					"spriteSourceSize": {
						"x": 0,
						"y": 0,
						"w": 900,
						"h": 900
					},
					"frame": {
						"x": 1103,
						"y": 1,
						"w": 900,
						"h": 900
					}
				},
				{
					"filename": "blackHoleArms.png",
					"rotated": false,
					"trimmed": true,
					"sourceSize": {
						"w": 1000,
						"h": 700
					},
					"spriteSourceSize": {
						"x": 0,
						"y": 12,
						"w": 1000,
						"h": 676
					},
					"frame": {
						"x": 1,
						"y": 1103,
						"w": 1000,
						"h": 676
					}
				},
				{
					"filename": "clock_back_large_red.png",
					"rotated": false,
					"trimmed": false,
					"sourceSize": {
						"w": 679,
						"h": 679
					},
					"spriteSourceSize": {
						"x": 0,
						"y": 0,
						"w": 679,
						"h": 679
					},
					"frame": {
						"x": 1103,
						"y": 903,
						"w": 679,
						"h": 679
					}
				},
				{
					"filename": "timeGreen.png",
					"rotated": false,
					"trimmed": false,
					"sourceSize": {
						"w": 200,
						"h": 200
					},
					"spriteSourceSize": {
						"x": 0,
						"y": 0,
						"w": 200,
						"h": 200
					},
					"frame": {
						"x": 1,
						"y": 1781,
						"w": 200,
						"h": 200
					}
				},
				{
					"filename": "timeRed.png",
					"rotated": false,
					"trimmed": false,
					"sourceSize": {
						"w": 200,
						"h": 200
					},
					"spriteSourceSize": {
						"x": 0,
						"y": 0,
						"w": 200,
						"h": 200
					},
					"frame": {
						"x": 203,
						"y": 1781,
						"w": 200,
						"h": 200
					}
				},
				{
					"filename": "usage_hover.png",
					"rotated": false,
					"trimmed": true,
					"sourceSize": {
						"w": 404,
						"h": 404
					},
					"spriteSourceSize": {
						"x": 4,
						"y": 4,
						"w": 396,
						"h": 396
					},
					"frame": {
						"x": 1003,
						"y": 1584,
						"w": 396,
						"h": 396
					}
				},
				{
					"filename": "blackHoleBig.png",
					"rotated": false,
					"trimmed": true,
					"sourceSize": {
						"w": 300,
						"h": 302
					},
					"spriteSourceSize": {
						"x": 12,
						"y": 13,
						"w": 280,
						"h": 228
					},
					"frame": {
						"x": 1401,
						"y": 1584,
						"w": 280,
						"h": 228
					}
				},
				{
					"filename": "eye.png",
					"rotated": false,
					"trimmed": true,
					"sourceSize": {
						"w": 306,
						"h": 164
					},
					"spriteSourceSize": {
						"x": 5,
						"y": 1,
						"w": 297,
						"h": 163
					},
					"frame": {
						"x": 405,
						"y": 1781,
						"w": 297,
						"h": 163
					}
				},
				{
					"filename": "mindBurn.png",
					"rotated": false,
					"trimmed": true,
					"sourceSize": {
						"w": 250,
						"h": 250
					},
					"spriteSourceSize": {
						"x": 6,
						"y": 10,
						"w": 228,
						"h": 237
					},
					"frame": {
						"x": 1784,
						"y": 903,
						"w": 228,
						"h": 237
					}
				},
				{
					"filename": "darkSlice.png",
					"rotated": false,
					"trimmed": true,
					"sourceSize": {
						"w": 200,
						"h": 300
					},
					"spriteSourceSize": {
						"x": 13,
						"y": 9,
						"w": 173,
						"h": 280
					},
					"frame": {
						"x": 1784,
						"y": 1142,
						"w": 173,
						"h": 280
					}
				},
				{
					"filename": "laserCore.png",
					"rotated": false,
					"trimmed": true,
					"sourceSize": {
						"w": 80,
						"h": 200
					},
					"spriteSourceSize": {
						"x": 7,
						"y": 0,
						"w": 65,
						"h": 200
					},
					"frame": {
						"x": 1959,
						"y": 1142,
						"w": 65,
						"h": 200
					}
				},
				{
					"filename": "stalagmite.png",
					"rotated": false,
					"trimmed": true,
					"sourceSize": {
						"w": 130,
						"h": 325
					},
					"spriteSourceSize": {
						"x": 0,
						"y": 2,
						"w": 126,
						"h": 323
					},
					"frame": {
						"x": 1683,
						"y": 1584,
						"w": 126,
						"h": 323
					}
				},
				{
					"filename": "blackHolePre.png",
					"rotated": false,
					"trimmed": true,
					"sourceSize": {
						"w": 165,
						"h": 165
					},
					"spriteSourceSize": {
						"x": 2,
						"y": 8,
						"w": 161,
						"h": 156
					},
					"frame": {
						"x": 704,
						"y": 1781,
						"w": 161,
						"h": 156
					}
				},
				{
					"filename": "clockShield.png",
					"rotated": false,
					"trimmed": true,
					"sourceSize": {
						"w": 267,
						"h": 225
					},
					"spriteSourceSize": {
						"x": 0,
						"y": 1,
						"w": 267,
						"h": 48
					},
					"frame": {
						"x": 1401,
						"y": 1814,
						"w": 267,
						"h": 48
					}
				},
				{
					"filename": "clock_arm_large.png",
					"rotated": false,
					"trimmed": false,
					"sourceSize": {
						"w": 286,
						"h": 28
					},
					"spriteSourceSize": {
						"x": 0,
						"y": 0,
						"w": 286,
						"h": 28
					},
					"frame": {
						"x": 405,
						"y": 1946,
						"w": 286,
						"h": 28
					}
				},
				{
					"filename": "stoneShield.png",
					"rotated": false,
					"trimmed": true,
					"sourceSize": {
						"w": 240,
						"h": 240
					},
					"spriteSourceSize": {
						"x": 0,
						"y": 5,
						"w": 240,
						"h": 69
					},
					"frame": {
						"x": 1784,
						"y": 1424,
						"w": 240,
						"h": 69
					}
				},
				{
					"filename": "mindEffect.png",
					"rotated": false,
					"trimmed": true,
					"sourceSize": {
						"w": 100,
						"h": 101
					},
					"spriteSourceSize": {
						"x": 1,
						"y": 1,
						"w": 98,
						"h": 99
					},
					"frame": {
						"x": 1003,
						"y": 1103,
						"w": 98,
						"h": 99
					}
				},
				{
					"filename": "matter_boost_2.png",
					"rotated": false,
					"trimmed": true,
					"sourceSize": {
						"w": 160,
						"h": 630
					},
					"spriteSourceSize": {
						"x": 3,
						"y": 4,
						"w": 126,
						"h": 178
					},
					"frame": {
						"x": 867,
						"y": 1781,
						"w": 126,
						"h": 178
					}
				},
				{
					"filename": "lightningBolt.png",
					"rotated": false,
					"trimmed": true,
					"sourceSize": {
						"w": 50,
						"h": 200
					},
					"spriteSourceSize": {
						"x": 3,
						"y": 1,
						"w": 45,
						"h": 197
					},
					"frame": {
						"x": 1003,
						"y": 1204,
						"w": 45,
						"h": 197
					}
				},
				{
					"filename": "shockEffect.png",
					"rotated": false,
					"trimmed": true,
					"sourceSize": {
						"w": 125,
						"h": 125
					},
					"spriteSourceSize": {
						"x": 6,
						"y": 5,
						"w": 111,
						"h": 113
					},
					"frame": {
						"x": 1401,
						"y": 1864,
						"w": 111,
						"h": 113
					}
				},
				{
					"filename": "eyeShield.png",
					"rotated": false,
					"trimmed": true,
					"sourceSize": {
						"w": 170,
						"h": 220
					},
					"spriteSourceSize": {
						"x": 0,
						"y": 0,
						"w": 170,
						"h": 47
					},
					"frame": {
						"x": 1784,
						"y": 1495,
						"w": 170,
						"h": 47
					}
				},
				{
					"filename": "bigRock.png",
					"rotated": false,
					"trimmed": true,
					"sourceSize": {
						"w": 150,
						"h": 150
					},
					"spriteSourceSize": {
						"x": 3,
						"y": 3,
						"w": 143,
						"h": 141
					},
					"frame": {
						"x": 1811,
						"y": 1544,
						"w": 143,
						"h": 141
					}
				},
				{
					"filename": "eyeCircle.png",
					"rotated": false,
					"trimmed": false,
					"sourceSize": {
						"w": 120,
						"h": 120
					},
					"spriteSourceSize": {
						"x": 0,
						"y": 0,
						"w": 120,
						"h": 120
					},
					"frame": {
						"x": 1811,
						"y": 1687,
						"w": 120,
						"h": 120
					}
				},
				{
					"filename": "damageEffect.png",
					"rotated": false,
					"trimmed": true,
					"sourceSize": {
						"w": 125,
						"h": 125
					},
					"spriteSourceSize": {
						"x": 9,
						"y": 1,
						"w": 112,
						"h": 122
					},
					"frame": {
						"x": 1811,
						"y": 1809,
						"w": 112,
						"h": 122
					}
				},
				{
					"filename": "matter_boost.png",
					"rotated": false,
					"trimmed": true,
					"sourceSize": {
						"w": 90,
						"h": 520
					},
					"spriteSourceSize": {
						"x": 10,
						"y": 7,
						"w": 71,
						"h": 97
					},
					"frame": {
						"x": 1514,
						"y": 1864,
						"w": 71,
						"h": 97
					}
				},
				{
					"filename": "impact.png",
					"rotated": false,
					"trimmed": false,
					"sourceSize": {
						"w": 81,
						"h": 70
					},
					"spriteSourceSize": {
						"x": 0,
						"y": 0,
						"w": 81,
						"h": 70
					},
					"frame": {
						"x": 1587,
						"y": 1864,
						"w": 81,
						"h": 70
					}
				},
				{
					"filename": "weakenLines_00.png",
					"rotated": false,
					"trimmed": true,
					"sourceSize": {
						"w": 70,
						"h": 50
					},
					"spriteSourceSize": {
						"x": 0,
						"y": 1,
						"w": 69,
						"h": 45
					},
					"frame": {
						"x": 1587,
						"y": 1936,
						"w": 69,
						"h": 45
					}
				},
				{
					"filename": "weakenLines_01.png",
					"rotated": false,
					"trimmed": true,
					"sourceSize": {
						"w": 70,
						"h": 50
					},
					"spriteSourceSize": {
						"x": 2,
						"y": 6,
						"w": 68,
						"h": 40
					},
					"frame": {
						"x": 1956,
						"y": 1495,
						"w": 68,
						"h": 40
					}
				},
				{
					"filename": "blackBolt.png",
					"rotated": false,
					"trimmed": false,
					"sourceSize": {
						"w": 50,
						"h": 100
					},
					"spriteSourceSize": {
						"x": 0,
						"y": 0,
						"w": 50,
						"h": 100
					},
					"frame": {
						"x": 1050,
						"y": 1204,
						"w": 50,
						"h": 100
					}
				},
				{
					"filename": "clock.png",
					"rotated": false,
					"trimmed": true,
					"sourceSize": {
						"w": 75,
						"h": 75
					},
					"spriteSourceSize": {
						"x": 10,
						"y": 5,
						"w": 55,
						"h": 64
					},
					"frame": {
						"x": 1959,
						"y": 1344,
						"w": 55,
						"h": 64
					}
				},
				{
					"filename": "rock.png",
					"rotated": false,
					"trimmed": true,
					"sourceSize": {
						"w": 75,
						"h": 75
					},
					"spriteSourceSize": {
						"x": 2,
						"y": 2,
						"w": 71,
						"h": 73
					},
					"frame": {
						"x": 1003,
						"y": 1403,
						"w": 71,
						"h": 73
					}
				},
				{
					"filename": "voidCharge.png",
					"rotated": false,
					"trimmed": true,
					"sourceSize": {
						"w": 300,
						"h": 40
					},
					"spriteSourceSize": {
						"x": 1,
						"y": 0,
						"w": 298,
						"h": 40
					},
					"frame": {
						"x": 1670,
						"y": 1933,
						"w": 298,
						"h": 40
					}
				},
				{
					"filename": "blackHoleSmall.png",
					"rotated": false,
					"trimmed": false,
					"sourceSize": {
						"w": 56,
						"h": 56
					},
					"spriteSourceSize": {
						"x": 0,
						"y": 0,
						"w": 56,
						"h": 56
					},
					"frame": {
						"x": 1003,
						"y": 1478,
						"w": 56,
						"h": 56
					}
				},
				{
					"filename": "blackCircle.png",
					"rotated": false,
					"trimmed": false,
					"sourceSize": {
						"w": 40,
						"h": 40
					},
					"spriteSourceSize": {
						"x": 0,
						"y": 0,
						"w": 40,
						"h": 40
					},
					"frame": {
						"x": 1061,
						"y": 1478,
						"w": 40,
						"h": 40
					}
				},
				{
					"filename": "energy_particle.png",
					"rotated": false,
					"trimmed": false,
					"sourceSize": {
						"w": 40,
						"h": 40
					},
					"spriteSourceSize": {
						"x": 0,
						"y": 0,
						"w": 40,
						"h": 40
					},
					"frame": {
						"x": 1061,
						"y": 1520,
						"w": 40,
						"h": 40
					}
				},
				{
					"filename": "time_red_mini.png",
					"rotated": false,
					"trimmed": false,
					"sourceSize": {
						"w": 25,
						"h": 25
					},
					"spriteSourceSize": {
						"x": 0,
						"y": 0,
						"w": 25,
						"h": 25
					},
					"frame": {
						"x": 1784,
						"y": 1544,
						"w": 25,
						"h": 25
					}
				},
				{
					"filename": "laserCircle.png",
					"rotated": false,
					"trimmed": true,
					"sourceSize": {
						"w": 64,
						"h": 16
					},
					"spriteSourceSize": {
						"x": 1,
						"y": 1,
						"w": 62,
						"h": 14
					},
					"frame": {
						"x": 1514,
						"y": 1963,
						"w": 62,
						"h": 14
					}
				},
				{
					"filename": "green_plus.png",
					"rotated": false,
					"trimmed": false,
					"sourceSize": {
						"w": 34,
						"h": 34
					},
					"spriteSourceSize": {
						"x": 0,
						"y": 0,
						"w": 34,
						"h": 34
					},
					"frame": {
						"x": 1050,
						"y": 1306,
						"w": 34,
						"h": 34
					}
				},
				{
					"filename": "voidParticle.png",
					"rotated": false,
					"trimmed": false,
					"sourceSize": {
						"w": 15,
						"h": 15
					},
					"spriteSourceSize": {
						"x": 0,
						"y": 0,
						"w": 15,
						"h": 15
					},
					"frame": {
						"x": 1086,
						"y": 1306,
						"w": 15,
						"h": 15
					}
				},
				{
					"filename": "rock_chip.png",
					"rotated": false,
					"trimmed": false,
					"sourceSize": {
						"w": 20,
						"h": 20
					},
					"spriteSourceSize": {
						"x": 0,
						"y": 0,
						"w": 20,
						"h": 20
					},
					"frame": {
						"x": 1933,
						"y": 1687,
						"w": 20,
						"h": 20
					}
				}
			]
		},
		{
			"image": "sprites/spells-1.webp",
			"format": "RGBA8888",
			"size": {
				"w": 1058,
				"h": 1650
			},
			"scale": 1,
			"frames": [
				{
					"filename": "clock_back_large.png",
					"rotated": false,
					"trimmed": true,
					"sourceSize": {
						"w": 613,
						"h": 613
					},
					"spriteSourceSize": {
						"x": 1,
						"y": 1,
						"w": 611,
						"h": 611
					},
					"frame": {
						"x": 1,
						"y": 1,
						"w": 611,
						"h": 611
					}
				},
				{
					"filename": "brickPattern1.png",
					"rotated": false,
					"trimmed": true,
					"sourceSize": {
						"w": 471,
						"h": 471
					},
					"spriteSourceSize": {
						"x": 14,
						"y": 13,
						"w": 443,
						"h": 446
					},
					"frame": {
						"x": 614,
						"y": 1,
						"w": 443,
						"h": 446
					}
				},
				{
					"filename": "rockCircle.png",
					"rotated": false,
					"trimmed": true,
					"sourceSize": {
						"w": 600,
						"h": 600
					},
					"spriteSourceSize": {
						"x": 8,
						"y": 4,
						"w": 570,
						"h": 596
					},
					"frame": {
						"x": 1,
						"y": 614,
						"w": 570,
						"h": 596
					}
				},
				{
					"filename": "shield.png",
					"rotated": false,
					"trimmed": true,
					"sourceSize": {
						"w": 500,
						"h": 440
					},
					"spriteSourceSize": {
						"x": 7,
						"y": 1,
						"w": 486,
						"h": 437
					},
					"frame": {
						"x": 1,
						"y": 1212,
						"w": 486,
						"h": 437
					}
				},
				{
					"filename": "brickPattern2.png",
					"rotated": false,
					"trimmed": true,
					"sourceSize": {
						"w": 471,
						"h": 471
					},
					"spriteSourceSize": {
						"x": 4,
						"y": 8,
						"w": 461,
						"h": 455
					},
					"frame": {
						"x": 573,
						"y": 614,
						"w": 461,
						"h": 455
					}
				},
				{
					"filename": "needlePattern.png",
					"rotated": false,
					"trimmed": true,
					"sourceSize": {
						"w": 470,
						"h": 470
					},
					"spriteSourceSize": {
						"x": 5,
						"y": 5,
						"w": 460,
						"h": 460
					},
					"frame": {
						"x": 573,
						"y": 1071,
						"w": 460,
						"h": 460
					}
				}
			]
		}
	],
	"meta": {
		"app": "https://www.codeandweb.com/texturepacker",
		"version": "3.0",
		"smartupdate": "$TexturePacker:SmartUpdate:63209349ff46cc040befdab8f809bd66:1dda3143a674f4b6a57e0b35a651930b:5e62eb201321ea33b301bbf963063802$"
	}
}
